[{"code": "pd.set_option(\"display.max_columns\", 70)\npd.set_option(\"display.max_rows\", 300)\n\nfor n in n_list:\n    data=np.zeros((n-1,n-1))\n    for i in range(1,n):\n        for j in range(1,n):\n            data[i-1][j-1] = int((i**j) % n )\n    df = pd.DataFrame(data, dtype='int')\n    df = df.rename(columns=lambda s:   'a**'+ str(s+1), index=lambda s: 'a=' +str(s+1) )\n    df\n    print('-----------------------')\n    print('mod('+str(n)+')')\n    display(df)", "path": "/home/yoko69d621/textbook/nw_sec/.log/20190922/20190922-043613-0630.log", "start": "2019-09-22 04:36:13(UTC)", "end": "2019-09-22 04:36:13(UTC)", "size": 1966, "server_signature": "5e786c6e-5fea-11e9-b810-02420a00005a", "uid": 1005, "gid": 100, "notebook_path": "textbook/nw_sec/12-security-fermat.ipynb", "lc_notebook_meme": "a8ff14d2-7f56-11e9-a4fd-02420a01012b", "execute_reply_status": "ok"}]